ctf_common/__init__.py
ctf_common/constants/__init__.py
ctf_common/constants/db_constants.py
ctf_common/constants/service_constants.py
ctf_common/enums/__init__.py
ctf_common/enums/common_enum.py
ctf_common/reports/__init__.py
ctf_common/reports/data_log_entry.py
ctf_common/reports/report_api.py
ctf_common/reports/report_data.py
ctf_common/reports/report_enums.py
ctf_common/reports/report_lock.py
ctf_common/reports/report_logger.py
ctf_common/reports/report_manager.py
ctf_common/reports/test_scopes.py
ctf_common/utils/__init__.py
ctf_common/utils/compare_log.py
ctf_common/utils/date_util.py
tests/__init__.py
tests/test_reports/__init__.py
tests/test_reports/test_report_api.py
ctf_common-0.1.5.dist-info/METADATA
ctf_common-0.1.5.dist-info/WHEEL
ctf_common-0.1.5.dist-info/top_level.txt
ctf_common-0.1.5.dist-info/RECORD
