Metadata-Version: 2.4
Name: ctf_common
Version: 0.1.5
Summary: Common library for CTF projects
Home-page: https://github.com/joanne-cyw/ctf_common
Author: Joanney Wang
Author-email: joanne.cyw@hotmail.com
Classifier: Programming Language :: Python :: 3
Classifier: License :: OSI Approved :: MIT License
Classifier: Operating System :: OS Independent
Requires-Python: >=3.7
Requires-Dist: requests>=2.31.0
Requires-Dist: pyyaml>=6.0.1
Dynamic: author
Dynamic: author-email
Dynamic: classifier
Dynamic: description
Dynamic: description-content-type
Dynamic: home-page
Dynamic: requires-dist
Dynamic: requires-python
Dynamic: summary
